bytes2string/__init__.py
bytes2string/bytes2string.py
bytes2string-0.1.0.dist-info/DESCRIPTION.rst
bytes2string-0.1.0.dist-info/METADATA
bytes2string-0.1.0.dist-info/RECORD
bytes2string-0.1.0.dist-info/WHEEL
bytes2string-0.1.0.dist-info/entry_points.txt
bytes2string-0.1.0.dist-info/metadata.json
bytes2string-0.1.0.dist-info/top_level.txt
sample/__init__.py
