Metadata-Version: 2.0
Name: bytes2string
Version: 0.1.0
Summary: Convert bytes to string and vice versa
Home-page: https://github.com/jvalansi/bytes2string
Author: Jordan Valansi
Author-email: jvalansi@gmail.com
License: MIT
Keywords: convert string utf8 bytes binary mp3
Platform: UNKNOWN
Classifier: Development Status :: 3 - Alpha
Classifier: Intended Audience :: Developers
Classifier: Topic :: Software Development :: Build Tools
Classifier: License :: OSI Approved :: MIT License
Classifier: Programming Language :: Python :: 3
Classifier: Programming Language :: Python :: 3.3
Classifier: Programming Language :: Python :: 3.4
Classifier: Programming Language :: Python :: 3.5
Provides-Extra: dev
Requires-Dist: check-manifest; extra == 'dev'
Provides-Extra: test
Requires-Dist: coverage; extra == 'test'
